stepan/__init__.py
stepan-1.0.3.data/scripts/mirmik-was-here
stepan-1.0.3.dist-info/METADATA
stepan-1.0.3.dist-info/RECORD
stepan-1.0.3.dist-info/WHEEL
stepan-1.0.3.dist-info/top_level.txt
