Metadata-Version: 2.1
Name: stepan
Version: 1.0.3
Summary: Stepan Library
Home-page: https://github.com/mirmik/stepan
Author: mirmik
Author-email: mirmikns@yandex.ru
License: MIT
Platform: UNKNOWN
